Metadata-Version: 1.0
Name: genopype
Version: 2020.3.27
Summary: Architecture for building creating pipelines
Home-page: https://github.com/jolespin/genopype
Author: Josh L. Espinoza
Author-email: jespinoz@jcvi.org
License: BSD-3
Platform: UNKNOWN
